{"info":{"title":"UserMs","version":"1.0.0","description":"USER REST OPERATION"},"host":"https://apibm.herokuapp.com","basePath":"/","swagger":"2.0","paths":{"definitions":{"User":{"properties":{"name":{"type":"string"},"firstname":{"type":"string"},"age":{"type":"string"},"sex":{"type":"string"},"adress":{"type":"string"},"password":{"type":"string"}}}},"/users":{"get":{"tags":["Users"],"description":"Returns all users","produces":["application/json"],"responses":{"200":{"description":"An array of users","schema":{"$ref":"#/definitions/User"}}}}},"/users/new":{"post":{"tags":["Users"],"description":"Creates a new user","produces":["application/json"],"parameters":[{"name":"user","description":"User object","in":"body","required":true,"schema":{"$ref":"#/definitions/User"}}],"responses":{"200":{"description":"Successfully created"}}}},"/users/delete":{"post":{"tags":["Users"],"description":"Deletes a single user","produces":["application/json"],"parameters":[{"name":"id","description":"user mongoDb id","in":"path","required":true,"type":"string"}],"responses":{"200":{"description":"Successfully deleted"}}}},"/users/find":{"post":{"tags":["Users"],"description":"Returns a single user","produces":["application/json"],"parameters":[{"name":"id","description":"user mongoDb id","in":"path","required":true,"type":"string"}],"responses":{"200":{"description":"A single user","schema":{"$ref":"#/definitions/User"}}}}}},"definitions":{},"responses":{},"parameters":{},"securityDefinitions":{}}